{
  "adsb": {
    "data": [],
    "live": true,
    "history": [
      {
        "id": "710102",
        "callsign": "710102",
        "alt": 0,
        "spd": 536,
        "hdg": 85,
        "lat": 0,
        "lon": 0,
        "dist": 0,
        "rssi": -60,
        "squawk": 0
      },
      {
        "id": "89650A",
        "callsign": "ETD931",
        "alt": 0,
        "spd": 0,
        "hdg": 0,
        "lat": 0,
        "lon": 0,
        "dist": 0,
        "rssi": -60,
        "squawk": 0
      },
      {
        "id": "70203E",
        "callsign": "70203E",
        "alt": 0,
        "spd": 0,
        "hdg": 0,
        "lat": 0,
        "lon": 0,
        "dist": 0,
        "rssi": -60,
        "squawk": 0
      },
      {
        "id": "06A079",
        "callsign": "06A079",
        "alt": 0,
        "spd": 546,
        "hdg": 86,
        "lat": 0,
        "lon": 0,
        "dist": 0,
        "rssi": -60,
        "squawk": 0
      },
      {
        "id": "8007B2",
        "callsign": "8007B2",
        "alt": 0,
        "spd": 0,
        "hdg": 0,
        "lat": 0,
        "lon": 0,
        "dist": 0,
        "rssi": -60,
        "squawk": 0
      },
      {
        "id": "4B187A",
        "callsign": "4B187A",
        "alt": 0,
        "spd": 0,
        "hdg": 0,
        "lat": 0,
        "lon": 0,
        "dist": 0,
        "rssi": -60,
        "squawk": 0
      },
      {
        "id": "70209B",
        "callsign": "70209B",
        "alt": 0,
        "spd": 0,
        "hdg": 0,
        "lat": 0,
        "lon": 0,
        "dist": 0,
        "rssi": -60,
        "squawk": 0
      },
      {
        "id": "89637C",
        "callsign": "89637C",
        "alt": 0,
        "spd": 209,
        "hdg": 278,
        "lat": 0,
        "lon": 0,
        "dist": 0,
        "rssi": -60,
        "squawk": 0
      },
      {
        "id": "89656C",
        "callsign": "89656C",
        "alt": 37000,
        "spd": 0,
        "hdg": 0,
        "lat": 0,
        "lon": 0,
        "dist": 0,
        "rssi": -60,
        "squawk": 0
      },
      {
        "id": "8013E4",
        "callsign": "8013E4",
        "alt": 0,
        "spd": 166,
        "hdg": 305,
        "lat": 0,
        "lon": 0,
        "dist": 0,
        "rssi": -60,
        "squawk": 0
      },
      {
        "id": "80052B",
        "callsign": "80052B",
        "alt": 0,
        "spd": 213,
        "hdg": 305,
        "lat": 0,
        "lon": 0,
        "dist": 0,
        "rssi": -60,
        "squawk": 0
      },
      {
        "id": "4B8467",
        "callsign": "4B8467",
        "alt": 0,
        "spd": 0,
        "hdg": 0,
        "lat": 0,
        "lon": 0,
        "dist": 0,
        "rssi": -60,
        "squawk": 0
      },
      {
        "id": "89665D",
        "callsign": "89665D",
        "alt": 0,
        "spd": 0,
        "hdg": 0,
        "lat": 0,
        "lon": 0,
        "dist": 0,
        "rssi": -60,
        "squawk": 0
      },
      {
        "id": "80053E",
        "callsign": "AIC5XK",
        "alt": 0,
        "spd": 0,
        "hdg": 0,
        "lat": 0,
        "lon": 0,
        "dist": 0,
        "rssi": -60,
        "squawk": 0
      },
      {
        "id": "801755",
        "callsign": "801755",
        "alt": 0,
        "spd": 148,
        "hdg": 225,
        "lat": 0,
        "lon": 0,
        "dist": 0,
        "rssi": -60,
        "squawk": 0
      },
      {
        "id": "7100C0",
        "callsign": "7100C0",
        "alt": 0,
        "spd": 542,
        "hdg": 85,
        "lat": 0,
        "lon": 0,
        "dist": 0,
        "rssi": -60,
        "squawk": 0
      },
      {
        "id": "8015C6",
        "callsign": "8015C6",
        "alt": 0,
        "spd": 0,
        "hdg": 0,
        "lat": 0,
        "lon": 0,
        "dist": 0,
        "rssi": -60,
        "squawk": 0
      },
      {
        "id": "80155A",
        "callsign": "80155A",
        "alt": 0,
        "spd": 0,
        "hdg": 0,
        "lat": 0,
        "lon": 0,
        "dist": 0,
        "rssi": -60,
        "squawk": 0
      },
      {
        "id": "8015E2",
        "callsign": "8015E2",
        "alt": 0,
        "spd": 236,
        "hdg": 304,
        "lat": 0,
        "lon": 0,
        "dist": 0,
        "rssi": -60,
        "squawk": 0
      },
      {
        "id": "800D40",
        "callsign": "800D40",
        "alt": 0,
        "spd": 0,
        "hdg": 0,
        "lat": 0,
        "lon": 0,
        "dist": 0,
        "rssi": -60,
        "squawk": 0
      },
      {
        "id": "7020AC",
        "callsign": "7020AC",
        "alt": 0,
        "spd": 0,
        "hdg": 0,
        "lat": 0,
        "lon": 0,
        "dist": 0,
        "rssi": -60,
        "squawk": 0
      },
      {
        "id": "801603",
        "callsign": "801603",
        "alt": 0,
        "spd": 0,
        "hdg": 0,
        "lat": 0,
        "lon": 0,
        "dist": 0,
        "rssi": -60,
        "squawk": 0
      },
      {
        "id": "89611B",
        "callsign": "89611B",
        "alt": 0,
        "spd": 0,
        "hdg": 0,
        "lat": 0,
        "lon": 0,
        "dist": 0,
        "rssi": -60,
        "squawk": 0
      },
      {
        "id": "750421",
        "callsign": "750421",
        "alt": 0,
        "spd": 0,
        "hdg": 0,
        "lat": 0,
        "lon": 0,
        "dist": 0,
        "rssi": -60,
        "squawk": 0
      },
      {
        "id": "801850",
        "callsign": "801850",
        "alt": 0,
        "spd": 0,
        "hdg": 0,
        "lat": 0,
        "lon": 0,
        "dist": 0,
        "rssi": -60,
        "squawk": 0
      },
      {
        "id": "7020BE",
        "callsign": "7020BE",
        "alt": 32000,
        "spd": 0,
        "hdg": 0,
        "lat": 0,
        "lon": 0,
        "dist": 0,
        "rssi": -60,
        "squawk": 0
      },
      {
        "id": "06A103",
        "callsign": "06A103",
        "alt": 0,
        "spd": 0,
        "hdg": 0,
        "lat": 0,
        "lon": 0,
        "dist": 0,
        "rssi": -60,
        "squawk": 0
      },
      {
        "id": "89653C",
        "callsign": "89653C",
        "alt": 0,
        "spd": 0,
        "hdg": 0,
        "lat": 0,
        "lon": 0,
        "dist": 0,
        "rssi": -60,
        "squawk": 0
      },
      {
        "id": "7020B4",
        "callsign": "7020B4",
        "alt": 0,
        "spd": 342,
        "hdg": 255,
        "lat": 0,
        "lon": 0,
        "dist": 0,
        "rssi": -60,
        "squawk": 0
      },
      {
        "id": "801405",
        "callsign": "801405",
        "alt": 0,
        "spd": 234,
        "hdg": 305,
        "lat": 0,
        "lon": 0,
        "dist": 0,
        "rssi": -60,
        "squawk": 0
      },
      {
        "id": "801405",
        "callsign": "801405",
        "alt": 0,
        "spd": 0,
        "hdg": 0,
        "lat": 0,
        "lon": 0,
        "dist": 0,
        "rssi": -60,
        "squawk": 0
      },
      {
        "id": "896535",
        "callsign": "ETD899",
        "alt": 0,
        "spd": 0,
        "hdg": 0,
        "lat": 0,
        "lon": 0,
        "dist": 0,
        "rssi": -60,
        "squawk": 0
      },
      {
        "id": "4BA869",
        "callsign": "4BA869",
        "alt": 41000,
        "spd": 0,
        "hdg": 0,
        "lat": 0,
        "lon": 0,
        "dist": 0,
        "rssi": -60,
        "squawk": 0
      },
      {
        "id": "4BA869",
        "callsign": "4BA869",
        "alt": 0,
        "spd": 0,
        "hdg": 0,
        "lat": 0,
        "lon": 0,
        "dist": 0,
        "rssi": -60,
        "squawk": 0
      },
      {
        "id": "8966BD",
        "callsign": "8966BD",
        "alt": 0,
        "spd": 0,
        "hdg": 0,
        "lat": 0,
        "lon": 0,
        "dist": 0,
        "rssi": -60,
        "squawk": 0
      },
      {
        "id": "801831",
        "callsign": "801831",
        "alt": 0,
        "spd": 235,
        "hdg": 282,
        "lat": 0,
        "lon": 0,
        "dist": 0,
        "rssi": -60,
        "squawk": 0
      },
      {
        "id": "800BEF",
        "callsign": "800BEF",
        "alt": 0,
        "spd": 0,
        "hdg": 0,
        "lat": 0,
        "lon": 0,
        "dist": 0,
        "rssi": -60,
        "squawk": 0
      },
      {
        "id": "8014F8",
        "callsign": "8014F8",
        "alt": 0,
        "spd": 267,
        "hdg": 299,
        "lat": 0,
        "lon": 0,
        "dist": 0,
        "rssi": -60,
        "squawk": 0
      },
      {
        "id": "8015DB",
        "callsign": "8015DB",
        "alt": 0,
        "spd": 258,
        "hdg": 7,
        "lat": 0,
        "lon": 0,
        "dist": 0,
        "rssi": -60,
        "squawk": 0
      },
      {
        "id": "06A1E8",
        "callsign": "06A1E8",
        "alt": 0,
        "spd": 536,
        "hdg": 86,
        "lat": 0,
        "lon": 0,
        "dist": 0,
        "rssi": -60,
        "squawk": 0
      },
      {
        "id": "896442",
        "callsign": "896442",
        "alt": 41000,
        "spd": 0,
        "hdg": 0,
        "lat": 0,
        "lon": 0,
        "dist": 0,
        "rssi": -60,
        "squawk": 0
      },
      {
        "id": "~6089F3",
        "callsign": "~6089F3",
        "alt": 0,
        "spd": 0,
        "hdg": 0,
        "lat": 0,
        "lon": 0,
        "dist": 0,
        "rssi": -60,
        "squawk": 0
      },
      {
        "id": "06A3B6",
        "callsign": "06A3B6",
        "alt": 37000,
        "spd": 0,
        "hdg": 0,
        "lat": 0,
        "lon": 0,
        "dist": 0,
        "rssi": -60,
        "squawk": 0
      },
      {
        "id": "800BE6",
        "callsign": "800BE6",
        "alt": 0,
        "spd": 0,
        "hdg": 0,
        "lat": 0,
        "lon": 0,
        "dist": 0,
        "rssi": -60,
        "squawk": 0
      },
      {
        "id": "80145A",
        "callsign": "80145A",
        "alt": 0,
        "spd": 0,
        "hdg": 0,
        "lat": 0,
        "lon": 0,
        "dist": 0,
        "rssi": -60,
        "squawk": 0
      },
      {
        "id": "710102",
        "callsign": "710102",
        "alt": 0,
        "spd": 0,
        "hdg": 0,
        "lat": 0,
        "lon": 0,
        "dist": 0,
        "rssi": -60,
        "squawk": 0
      },
      {
        "id": "70203E",
        "callsign": "70203E",
        "alt": 34000,
        "spd": 0,
        "hdg": 0,
        "lat": 0,
        "lon": 0,
        "dist": 0,
        "rssi": -60,
        "squawk": 0
      },
      {
        "id": "040062",
        "callsign": "040062",
        "alt": 0,
        "spd": 0,
        "hdg": 0,
        "lat": 0,
        "lon": 0,
        "dist": 0,
        "rssi": -60,
        "squawk": 0
      },
      {
        "id": "800C99",
        "callsign": "800C99",
        "alt": 0,
        "spd": 179,
        "hdg": 2,
        "lat": 0,
        "lon": 0,
        "dist": 0,
        "rssi": -60,
        "squawk": 0
      },
      {
        "id": "8965D4",
        "callsign": "8965D4",
        "alt": 35000,
        "spd": 0,
        "hdg": 0,
        "lat": 0,
        "lon": 0,
        "dist": 0,
        "rssi": -60,
        "squawk": 0
      },
      {
        "id": "896306",
        "callsign": "896306",
        "alt": 0,
        "spd": 541,
        "hdg": 86,
        "lat": 0,
        "lon": 0,
        "dist": 0,
        "rssi": -60,
        "squawk": 0
      },
      {
        "id": "8963CE",
        "callsign": "8963CE",
        "alt": 2300,
        "spd": 247,
        "hdg": 301,
        "lat": 0,
        "lon": 0,
        "dist": 0,
        "rssi": -60,
        "squawk": 0
      },
      {
        "id": "8963E3",
        "callsign": "8963E3",
        "alt": 30000,
        "spd": 0,
        "hdg": 0,
        "lat": 0,
        "lon": 0,
        "dist": 0,
        "rssi": -60,
        "squawk": 0
      },
      {
        "id": "89660C",
        "callsign": "89660C",
        "alt": 30000,
        "spd": 0,
        "hdg": 0,
        "lat": 0,
        "lon": 0,
        "dist": 0,
        "rssi": -60,
        "squawk": 0
      }
    ]
  },
  "wifi": {
    "data": [
      {
        "id": "ea:12:c6:b9:be:90",
        "ssid": "Redmi Note 11 Pro+ 5G",
        "bssid": "ea:12:c6:b9:be:90",
        "ch": "2462",
        "rssi": -82,
        "enc": "WPA2",
        "band": "2.4GHz",
        "cli": 0,
        "source": "nethunter"
      },
      {
        "id": "a8:da:0c:4e:94:90",
        "ssid": "Mishku 5G",
        "bssid": "a8:da:0c:4e:94:90",
        "ch": "5745",
        "rssi": -84,
        "enc": "WPA2",
        "band": "5GHz",
        "cli": 0,
        "source": "nethunter"
      },
      {
        "id": "b0:be:76:67:95:8c",
        "ssid": "JIOFIBERNET",
        "bssid": "b0:be:76:67:95:8c",
        "ch": "2452",
        "rssi": -75,
        "enc": "WPA2",
        "band": "2.4GHz",
        "cli": 0,
        "source": "nethunter"
      },
      {
        "id": "6c:4f:89:de:35:15",
        "ssid": "Airtel_Abhishek",
        "bssid": "6c:4f:89:de:35:15",
        "ch": "2412",
        "rssi": -81,
        "enc": "Open",
        "band": "2.4GHz",
        "cli": 0,
        "source": "nethunter"
      },
      {
        "id": "5e:a4:f4:2a:df:6a",
        "ssid": "Mitesh GTPL\\x20",
        "bssid": "5e:a4:f4:2a:df:6a",
        "ch": "2432",
        "rssi": -70,
        "enc": "WPA2",
        "band": "2.4GHz",
        "cli": 0,
        "source": "nethunter"
      },
      {
        "id": "8e:a3:99:36:fe:da",
        "ssid": "Hidden",
        "bssid": "8e:a3:99:36:fe:da",
        "ch": "5805",
        "rssi": -78,
        "enc": "WPA2",
        "band": "5GHz",
        "cli": 0,
        "source": "nethunter"
      },
      {
        "id": "9c:d4:a6:1d:30:53",
        "ssid": "Jio_4G",
        "bssid": "9c:d4:a6:1d:30:53",
        "ch": "2412",
        "rssi": -80,
        "enc": "WPA2",
        "band": "2.4GHz",
        "cli": 0,
        "source": "nethunter"
      },
      {
        "id": "6a:90:0a:d6:94:11",
        "ssid": "PRAGNESH",
        "bssid": "6a:90:0a:d6:94:11",
        "ch": "2412",
        "rssi": -82,
        "enc": "WPA2",
        "band": "2.4GHz",
        "cli": 0,
        "source": "nethunter"
      },
      {
        "id": "72:88:1f:17:13:a9",
        "ssid": "SUNIL",
        "bssid": "72:88:1f:17:13:a9",
        "ch": "2437",
        "rssi": -81,
        "enc": "WPA2",
        "band": "2.4GHz",
        "cli": 0,
        "source": "nethunter"
      },
      {
        "id": "8c:a3:99:16:fe:da",
        "ssid": "Airtel_RC Patel",
        "bssid": "8c:a3:99:16:fe:da",
        "ch": "5805",
        "rssi": -78,
        "enc": "WPA2",
        "band": "5GHz",
        "cli": 0,
        "source": "nethunter"
      },
      {
        "id": "b4:a7:c6:6a:59:49",
        "ssid": "Hexor_HRLS",
        "bssid": "b4:a7:c6:6a:59:49",
        "ch": "2462",
        "rssi": -54,
        "enc": "WPA2",
        "band": "2.4GHz",
        "cli": 0,
        "source": "nethunter"
      },
      {
        "id": 14,
        "ssid": "Hidden",
        "bssid": "00:00:00:00:00:00",
        "ch": 0,
        "rssi": -80,
        "enc": "WPA2",
        "band": "2.4GHz",
        "cli": 0,
        "source": "nethunter"
      },
      {
        "id": "b4:a7:c6:6a:59:4a",
        "ssid": "Hexor_LRHS",
        "bssid": "b4:a7:c6:6a:59:4a",
        "ch": "5785",
        "rssi": -64,
        "enc": "WPA2",
        "band": "5GHz",
        "cli": 0,
        "source": "nethunter"
      },
      {
        "id": "8c:a3:99:16:fe:d9",
        "ssid": "Airtel_RC Patel",
        "bssid": "8c:a3:99:16:fe:d9",
        "ch": "2412",
        "rssi": -74,
        "enc": "Open",
        "band": "2.4GHz",
        "cli": 0,
        "source": "nethunter"
      },
      {
        "id": 0,
        "ssid": "Reliance_JioFiber",
        "bssid": "36:16:01:15:f9:30",
        "ch": 36,
        "rssi": -1041,
        "enc": "WPA2",
        "cli": 7,
        "band": "2.4GHz"
      },
      {
        "id": 1,
        "ssid": "AndroidAP_8B3F",
        "bssid": "f8:49:ab:3e:c6:97",
        "ch": 36,
        "rssi": -1075,
        "enc": "WPA2",
        "cli": 7,
        "band": "5GHz"
      },
      {
        "id": 2,
        "ssid": "Corp_Office_5G",
        "bssid": "95:96:43:62:a2:d1",
        "ch": 44,
        "rssi": -1087,
        "enc": "WPA2",
        "cli": 6,
        "band": "5GHz"
      },
      {
        "id": 3,
        "ssid": "Corp_Office_5G",
        "bssid": "bc:92:85:03:91:76",
        "ch": 11,
        "rssi": -988,
        "enc": "WPA2",
        "cli": 11,
        "band": "2.4GHz"
      },
      {
        "id": 4,
        "ssid": "Guest_Net",
        "bssid": "06:d5:7d:26:48:78",
        "ch": 44,
        "rssi": -1015,
        "enc": "WPA3",
        "cli": 9,
        "band": "5GHz"
      },
      {
        "id": 5,
        "ssid": "HP_Printer_78A",
        "bssid": "c2:8f:68:19:ef:10",
        "ch": 6,
        "rssi": -1043,
        "enc": "WPA3",
        "cli": 1,
        "band": "5GHz"
      },
      {
        "id": 6,
        "ssid": "Guest_Net",
        "bssid": "8e:b5:66:81:97:22",
        "ch": 6,
        "rssi": -886,
        "enc": "Open",
        "cli": 7,
        "band": "5GHz"
      },
      {
        "id": 7,
        "ssid": "TP-Link_3F2A",
        "bssid": "a2:5d:15:3e:64:cd",
        "ch": 11,
        "rssi": -1087,
        "enc": "Open",
        "cli": 11,
        "band": "2.4GHz"
      },
      {
        "id": 8,
        "ssid": "DIRECT-Fire",
        "bssid": "8a:7c:94:6d:5e:62",
        "ch": 44,
        "rssi": -1149,
        "enc": "WPA2",
        "cli": 8,
        "band": "5GHz"
      },
      {
        "id": 9,
        "ssid": "Corp_Office_5G",
        "bssid": "69:3f:3c:f7:e1:0f",
        "ch": 40,
        "rssi": -950,
        "enc": "WPA2",
        "cli": 5,
        "band": "5GHz"
      }
    ],
    "live": true
  },
  "ble": {
    "data": [
      {
        "id": 0,
        "name": "ESP32-BLE",
        "mac": "c7:7c:4b:8a:7c:fa",
        "rssi": -1206,
        "type": "Audio",
        "seen": 1775232966395
      },
      {
        "id": 1,
        "name": "Sony WH-1000",
        "mac": "48:c5:c5:43:05:d7",
        "rssi": -1269,
        "type": "Wearable",
        "seen": 1775233162092
      },
      {
        "id": 2,
        "name": "Sony WH-1000",
        "mac": "ba:37:54:c9:b5:cc",
        "rssi": -1287,
        "type": "Unknown",
        "seen": 1775233185554
      },
      {
        "id": 3,
        "name": "Mi Band 7",
        "mac": "26:c7:d6:b7:62:17",
        "rssi": -1344,
        "type": "Wearable",
        "seen": 1775233198416
      },
      {
        "id": 4,
        "name": "Fitbit Versa",
        "mac": "ac:47:75:57:a5:d0",
        "rssi": -1249,
        "type": "Wearable",
        "seen": 1775233041160
      },
      {
        "id": 5,
        "name": "Galaxy S23",
        "mac": "e5:03:8f:27:59:15",
        "rssi": -1291,
        "type": "IoT",
        "seen": 1775233090750
      },
      {
        "id": 6,
        "name": "ESP32-BLE",
        "mac": "10:bd:d8:56:ed:1a",
        "rssi": -1162,
        "type": "Audio",
        "seen": 1775233046263
      },
      {
        "id": 7,
        "name": "AirPods Pro",
        "mac": "d3:fc:fe:a0:0e:07",
        "rssi": -1394,
        "type": "Phone",
        "seen": 1775233204789
      },
      {
        "id": 8,
        "name": "Sony WH-1000",
        "mac": "9a:b0:a0:31:27:33",
        "rssi": -1231,
        "type": "Wearable",
        "seen": 1775233129458
      }
    ],
    "live": false
  },
  "rf433": {
    "data": [
      {
        "id": "d633d",
        "proto": "Sensor/Alarm Device",
        "freq": "433.92",
        "data": "0X77C0FFC002807DFC",
        "rssi": -56,
        "lqi": 127,
        "len": 63,
        "ts": 877373
      },
      {
        "id": "160fe3",
        "proto": "Too Short",
        "freq": "433.92",
        "data": "0XD0",
        "rssi": -55,
        "lqi": 127,
        "len": 1,
        "ts": 1445859
      },
      {
        "id": "f2f04",
        "proto": "Too Short",
        "freq": "433.92",
        "data": "0X20",
        "rssi": -49,
        "lqi": 127,
        "len": 1,
        "ts": 995076
      },
      {
        "id": "28d4f",
        "proto": "Sensor/Alarm Device",
        "freq": "433.92",
        "data": "0X7FDC00021E9AE401",
        "rssi": -51,
        "lqi": 127,
        "len": 63,
        "ts": 167247
      },
      {
        "id": "3e626",
        "proto": "Unknown 433 MHz",
        "freq": "433.92",
        "data": "0X575F00A02EBFDE00",
        "rssi": -50,
        "lqi": 127,
        "len": 9,
        "ts": 255527
      },
      {
        "id": "1047de",
        "proto": "Sensor/Alarm Device",
        "freq": "433.92",
        "data": "0XB6FB200000000000",
        "rssi": -55,
        "lqi": 127,
        "len": 45,
        "ts": 1066974
      },
      {
        "id": "5178a",
        "proto": "Unknown 433 MHz",
        "freq": "433.92",
        "data": "0XE000000000028D",
        "rssi": -51,
        "lqi": 127,
        "len": 7,
        "ts": 333706
      },
      {
        "id": "2e700",
        "proto": "Sensor/Alarm Device",
        "freq": "433.92",
        "data": "0XB7E40401FF101000",
        "rssi": -55,
        "lqi": 127,
        "len": 15,
        "ts": 190209
      },
      {
        "id": "2bc9c",
        "proto": "Sensor/Alarm Device",
        "freq": "433.92",
        "data": "0XEAFFFE0002004514",
        "rssi": -51,
        "lqi": 127,
        "len": 31,
        "ts": 179356
      },
      {
        "id": "38c0a",
        "proto": "Unknown 433 MHz",
        "freq": "433.92",
        "data": "0X83B30000",
        "rssi": -50,
        "lqi": 127,
        "len": 4,
        "ts": 232459
      },
      {
        "id": "9b426",
        "proto": "Sensor/Alarm Device",
        "freq": "433.92",
        "data": "0X6F7E000069DDBEEF",
        "rssi": -51,
        "lqi": 127,
        "len": 63,
        "ts": 635942
      },
      {
        "id": "57ed1",
        "proto": "Unknown 433 MHz",
        "freq": "433.92",
        "data": "0X9BDEEFFD",
        "rssi": -55,
        "lqi": 127,
        "len": 4,
        "ts": 360145
      },
      {
        "id": "5c317",
        "proto": "EV1527 Remote",
        "freq": "433.92",
        "data": "0X13F900",
        "rssi": -50,
        "lqi": 127,
        "len": 3,
        "ts": 377623
      },
      {
        "id": "3ba8",
        "proto": "Sensor/Alarm Device",
        "freq": "433.92",
        "data": "0X18F9F91DF3EFD004",
        "rssi": -57,
        "lqi": 127,
        "len": 35,
        "ts": 15272
      },
      {
        "id": "test123",
        "proto": "Test Protocol",
        "freq": "433.92",
        "data": "0xDEADBEEF",
        "raw": {
          "model": "test"
        },
        "rssi": -60,
        "ts": 1640995200000
      },
      {
        "id": "115a7",
        "proto": "Unknown 433 MHz",
        "freq": "433.92",
        "data": "0XBB2FFF8003ACF3",
        "rssi": -50,
        "lqi": 127,
        "len": 7,
        "ts": 71080
      },
      {
        "id": "ea467",
        "proto": "Sensor/Alarm Device",
        "freq": "433.92",
        "data": "0XFDFFD737F495FFEF",
        "rssi": -65,
        "lqi": 127,
        "len": 53,
        "ts": 959591
      },
      {
        "id": "test123",
        "proto": "Test Protocol",
        "freq": "433.92",
        "data": "0xDEADBEEF",
        "raw": {
          "model": "test"
        },
        "rssi": -60,
        "ts": 1640995200000
      }
    ],
    "live": true
  },
  "nrf24": {
    "data": [
      {
        "ch": 0,
        "v": 1
      },
      {
        "ch": 1,
        "v": 5
      },
      {
        "ch": 2,
        "v": 1
      },
      {
        "ch": 3,
        "v": 11
      },
      {
        "ch": 4,
        "v": 0
      },
      {
        "ch": 5,
        "v": 4
      },
      {
        "ch": 6,
        "v": 9
      },
      {
        "ch": 7,
        "v": 71
      },
      {
        "ch": 8,
        "v": 62
      },
      {
        "ch": 9,
        "v": 11
      },
      {
        "ch": 10,
        "v": 10
      },
      {
        "ch": 11,
        "v": 6
      },
      {
        "ch": 12,
        "v": 0
      },
      {
        "ch": 13,
        "v": 7
      },
      {
        "ch": 14,
        "v": 7
      },
      {
        "ch": 15,
        "v": 11
      },
      {
        "ch": 16,
        "v": 20
      },
      {
        "ch": 17,
        "v": 3
      },
      {
        "ch": 18,
        "v": 0
      },
      {
        "ch": 19,
        "v": 2
      },
      {
        "ch": 20,
        "v": 11
      },
      {
        "ch": 21,
        "v": 10
      },
      {
        "ch": 22,
        "v": 7
      },
      {
        "ch": 23,
        "v": 7
      },
      {
        "ch": 24,
        "v": 10
      },
      {
        "ch": 25,
        "v": 76
      },
      {
        "ch": 26,
        "v": 97
      },
      {
        "ch": 27,
        "v": 2
      },
      {
        "ch": 28,
        "v": 56
      },
      {
        "ch": 29,
        "v": 1
      },
      {
        "ch": 30,
        "v": 0
      },
      {
        "ch": 31,
        "v": 9
      },
      {
        "ch": 32,
        "v": 6
      },
      {
        "ch": 33,
        "v": 9
      },
      {
        "ch": 34,
        "v": 7
      },
      {
        "ch": 35,
        "v": 72
      },
      {
        "ch": 36,
        "v": 55
      },
      {
        "ch": 37,
        "v": 76
      },
      {
        "ch": 38,
        "v": 4
      },
      {
        "ch": 39,
        "v": 10
      },
      {
        "ch": 40,
        "v": 8
      },
      {
        "ch": 41,
        "v": 2
      },
      {
        "ch": 42,
        "v": 11
      },
      {
        "ch": 43,
        "v": 7
      },
      {
        "ch": 44,
        "v": 3
      },
      {
        "ch": 45,
        "v": 0
      },
      {
        "ch": 46,
        "v": 11
      },
      {
        "ch": 47,
        "v": 5
      },
      {
        "ch": 48,
        "v": 4
      },
      {
        "ch": 49,
        "v": 26
      },
      {
        "ch": 50,
        "v": 2
      },
      {
        "ch": 51,
        "v": 8
      },
      {
        "ch": 52,
        "v": 7
      },
      {
        "ch": 53,
        "v": 93
      },
      {
        "ch": 54,
        "v": 23
      },
      {
        "ch": 55,
        "v": 10
      },
      {
        "ch": 56,
        "v": 5
      },
      {
        "ch": 57,
        "v": 4
      },
      {
        "ch": 58,
        "v": 82
      },
      {
        "ch": 59,
        "v": 49
      },
      {
        "ch": 60,
        "v": 2
      },
      {
        "ch": 61,
        "v": 10
      },
      {
        "ch": 62,
        "v": 11
      },
      {
        "ch": 63,
        "v": 1
      },
      {
        "ch": 64,
        "v": 4
      },
      {
        "ch": 65,
        "v": 93
      },
      {
        "ch": 66,
        "v": 1
      },
      {
        "ch": 67,
        "v": 3
      },
      {
        "ch": 68,
        "v": 80
      },
      {
        "ch": 69,
        "v": 10
      },
      {
        "ch": 70,
        "v": 69
      },
      {
        "ch": 71,
        "v": 5
      },
      {
        "ch": 72,
        "v": 5
      },
      {
        "ch": 73,
        "v": 5
      },
      {
        "ch": 74,
        "v": 8
      },
      {
        "ch": 75,
        "v": 4
      },
      {
        "ch": 76,
        "v": 7
      },
      {
        "ch": 77,
        "v": 6
      },
      {
        "ch": 78,
        "v": 1
      },
      {
        "ch": 79,
        "v": 5
      },
      {
        "ch": 80,
        "v": 5
      },
      {
        "ch": 81,
        "v": 2
      },
      {
        "ch": 82,
        "v": 23
      },
      {
        "ch": 83,
        "v": 8
      },
      {
        "ch": 84,
        "v": 31
      },
      {
        "ch": 85,
        "v": 4
      },
      {
        "ch": 86,
        "v": 1
      },
      {
        "ch": 87,
        "v": 58
      },
      {
        "ch": 88,
        "v": 91
      },
      {
        "ch": 89,
        "v": 83
      },
      {
        "ch": 90,
        "v": 10
      },
      {
        "ch": 91,
        "v": 0
      },
      {
        "ch": 92,
        "v": 7
      },
      {
        "ch": 93,
        "v": 0
      },
      {
        "ch": 94,
        "v": 4
      },
      {
        "ch": 95,
        "v": 3
      },
      {
        "ch": 96,
        "v": 7
      },
      {
        "ch": 97,
        "v": 10
      },
      {
        "ch": 98,
        "v": 3
      },
      {
        "ch": 99,
        "v": 2
      },
      {
        "ch": 100,
        "v": 0
      },
      {
        "ch": 101,
        "v": 3
      },
      {
        "ch": 102,
        "v": 11
      },
      {
        "ch": 103,
        "v": 10
      },
      {
        "ch": 104,
        "v": 3
      },
      {
        "ch": 105,
        "v": 0
      },
      {
        "ch": 106,
        "v": 25
      },
      {
        "ch": 107,
        "v": 9
      },
      {
        "ch": 108,
        "v": 36
      },
      {
        "ch": 109,
        "v": 2
      },
      {
        "ch": 110,
        "v": 83
      },
      {
        "ch": 111,
        "v": 3
      },
      {
        "ch": 112,
        "v": 11
      },
      {
        "ch": 113,
        "v": 63
      },
      {
        "ch": 114,
        "v": 10
      },
      {
        "ch": 115,
        "v": 2
      },
      {
        "ch": 116,
        "v": 11
      },
      {
        "ch": 117,
        "v": 6
      },
      {
        "ch": 118,
        "v": 6
      },
      {
        "ch": 119,
        "v": 2
      },
      {
        "ch": 120,
        "v": 0
      },
      {
        "ch": 121,
        "v": 8
      },
      {
        "ch": 122,
        "v": 6
      },
      {
        "ch": 123,
        "v": 1
      },
      {
        "ch": 124,
        "v": 6
      },
      {
        "ch": 125,
        "v": 5
      }
    ],
    "live": false
  },
  "lora": {
    "data": [],
    "live": false
  },
  "nethunter": {
    "hosts": [],
    "live": false
  },
  "pwnagotchi": {
    "captures": 3143,
    "mood": "bored",
    "epoch": 0,
    "live": false
  },
  "alerts": [
    {
      "id": "vbpcsk9esfe",
      "msg": "Flight detected: 89660C",
      "sev": "info",
      "ts": 1775232887728
    },
    {
      "id": "mgr1qv6veor",
      "msg": "Flight detected: 8963E3",
      "sev": "info",
      "ts": 1775232293863
    }
  ]
}